ddr_simple.v
module ddr_simple (
    input  wire clk,       
    input  wire rst_n,     
    input  wire d_rise,    
    input  wire d_fall,    
    output reg  q          
);

    always @(posedge clk or negedge rst_n) begin
        if (!rst_n)
            q <= 1'b0;
        else
            q <= d_rise;  
    end

    always @(negedge clk or negedge rst_n) begin
        if (!rst_n)
            q <= 1'b0;
        else
            q <= d_fall;  
    end

endmodule

ddr_tb.sv
`timescale 1ns/1ps

module ddr_tb;

    reg clk;
    reg rst_n;
    reg d_rise;
    reg d_fall;
    wire q;

    ddr_simple uut (
        .clk(clk),
        .rst_n(rst_n),
        .d_rise(d_rise),
        .d_fall(d_fall),
        .q(q)
    );

    initial begin
        clk = 0;
        forever #5 clk = ~clk;  // Toggle every 5ns
    end

    initial begin
        rst_n = 0;
        d_rise = 0;
        d_fall = 0;
        #12 rst_n = 1;   // Release reset

        // Apply test patterns
        #10 d_rise = 1; d_fall = 0;
        #10 d_rise = 0; d_fall = 1;
        #10 d_rise = 1; d_fall = 1;
        #10 d_rise = 0; d_fall = 0;

        #50 $finish;
    end

    initial begin
        $monitor("Time=%0t |reset=%b| clk=%b | d_rise=%b | d_fall=%b | q=%b",
                  $time, rst_n, clk, d_rise, d_fall, q);
    end
    
initial begin
  $dumpfile("dump.vcd");
  $dumpvars(0, ddr_tb);
end

endmodule

dump.vcd
$date
	Wed May 20 15:32:07 2026
$end
$version
	Icarus Verilog
$end
$timescale
	1ps
$end
$scope module ddr_tb $end
$var wire 1 ! q $end
$var reg 1 " clk $end
$var reg 1 # d_fall $end
$var reg 1 $ d_rise $end
$var reg 1 % rst_n $end
$scope module uut $end
$var wire 1 " clk $end
$var wire 1 # d_fall $end
$var wire 1 $ d_rise $end
$var wire 1 % rst_n $end
$var reg 1 ! q $end
$upscope $end
$upscope $end
$enddefinitions $end
$comment Show the parameter values. $end
$dumpall
$end
#0
$dumpvars
0%
0$
0#
0"
0!
$end
#5000
1"
#10000
0"
#12000
1%
#15000
1"
#20000
0"
#22000
1$
#25000
1!
1"
#30000
0!
0"
#32000
1#
0$
#35000
1"
#40000
1!
0"
#42000
1$
#45000
1"
#50000
0"
#52000
0#
0$
#55000
0!
1"
